{
    "version": "r17.11",
    "build_time:": "2020-04-14 08:28:56",
    "compatible": "PyArmor >= 5.6.0",
    "changes": "Check license periodly",
    "remark": "",
    "platforms": [
        {
            "id": "windows.x86.7",
            "name": "windows.x86",
            "platform": "windows",
            "path": "win32",
            "machines": ["x86"],
            "features": ["JIT", "ANTI-DEBUG", "ADV"],
            "filename": "_pytransform.dll",
            "sha256": "16c5ec34d5fe54d750edccff59251212acbea8b74c3d901a96e56805e03eb365",
            "remark": "Cross compile by x86_64-w64-mingw32-gcc in cygwin"
        },
        {
            "id": "windows.x86_64.7",
            "name": "windows.x86_64",
            "platform": "windows",
            "path": "win_amd64",
            "machines": ["amd64", "x86_64", "x64"],
            "features": ["JIT", "ANTI-DEBUG", "ADV"],
            "filename": "_pytransform.dll",
            "sha256": "a6b31b73090dfb7e23ab05458ab1892ab429a91b171483bfeb6ebd526afc0d3c",
            "remark": "Cross compile by x86_64-w64-mingw32-gcc in cygwin"
        },
        {
            "id": "linux.x86.7",
            "name": "linux.x86",
            "platform": "linux",
            "path": "linux_i386",
            "machines": ["i386", "i486", "i586", "i686", "x86"],
            "features": ["JIT", "ANTI-DEBUG", "ADV"],
            "filename": "_pytransform.so",
            "sha256": "dc25bfea2b85ed5d0b0e105b7a2b82bb8cca6379a4ffb5c769463a32b17e20d2",
            "remark": "Built by GCC"
        },
        {
            "id": "linux.x86_64.7",
            "name": "linux.x86_64",
            "platform": "linux",
            "path": "linux_x86_64",
            "machines": ["x86_64", "amd64", "x64"],
            "features": ["JIT", "ANTI-DEBUG", "ADV"],
            "filename": "_pytransform.so",
            "sha256": "cf2f6ec9cb0dcac099bc87516c75afc17607291c4200f1c7a4dc55c9b26930e3",
            "remark": "Built by GCC"
        },
        {
            "id": "darwin.x86_64.7",
            "name": "darwin.x86_64",
            "platform": "darwin",
            "path": "macosx_x86_64",
            "machines": ["x86_64", "intel", "amd64", "x64"],
            "features": ["JIT", "ANTI-DEBUG", "ADV"],
            "filename": "_pytransform.dylib",
            "sha256": "4bd48ccefb550456950f3ea4933fb0b02305b775fa103d4cdd1fb5842078cca8",
            "remark": "Built by CLang with MacOSX10.11"
        },
        {
            "id": "vs2015.x86.0",
            "name": "vs2015.x86",
            "platform": "windows",
            "path": "vs2015.x86",
            "machines": ["x86"],
            "features": [],
            "filename": "_pytransform.dll",
            "sha256": "889ba799db4710007583f926d2246d27a17d8f787686f371aa8f46aa69d08023",
            "remark": "Built by VS2015"
        },
        {
            "id": "vs2015.x86_64.0",
            "name": "vs2015.x86_64",
            "platform": "windows",
            "path": "vs2015.x64",
            "machines": ["x64", "amd64"],
            "features": [],
            "filename": "_pytransform.dll",
            "sha256": "0da6b0ab22f1f7bdaa56b1585e311dea3555a70a22661cfc124f049035676f2a",
            "remark": "Built by VS2015"
        },
        {
            "id": "linux.arm.0",
            "name": "linux.arm",
            "platform": "linux",
            "path": "armv5",
            "machines": ["armv5"],
            "features": [],
            "filename": "_pytransform.so",
            "sha256": "980e610f2fb28375b7db4d0701483067a549edec84dff75e9747ebde0929e124",
            "remark": "32-bit Armv5 (arm926ej-s)"
        },
        {
            "id": "linux.armv7.3",
            "name": "linux.armv7",
            "platform": "linux",
            "path": "armv7",
            "machines": ["armv7l"],
            "features": ["JIT", "ANTI-DEBUG"],
            "filename": "_pytransform.so",
            "sha256": "fb2e6f870eb80e79e45da84470572cd8bfdb034922f559bbb5006da025b7dc03",
            "remark": "32-bit Armv7 Cortex-A, hard-float, little-endian"
        },
        {
            "id": "linux.aarch32.3",
            "name": "linux.aarch32",
            "platform": "linux",
            "path": "armv8.32-bit",
            "machines": ["aarch32"],
            "features": ["JIT", "ANTI-DEBUG"],
            "filename": "_pytransform.so",
            "sha256": "82b1ffa2243e7eb0fe4ff4bb6a07984312ea5cfa98be237f50313c0ba64d0c9a",
            "remark": "32-bit Armv8 Cortex-A, hard-float, little-endian"
        },
        {
            "id": "linux.aarch64.3",
            "name": "linux.aarch64",
            "platform": "linux",
            "path": "armv8.64-bit",
            "machines": ["aarch64"],
            "features": ["JIT", "ANTI-DEBUG"],
            "filename": "_pytransform.so",
            "sha256": "a57e8d48c45048dac767d382d6f206681dd65de9a38212630ca56108810241cd",
            "remark": "64-bit Armv8 Cortex-A, little-endian"
        },
        {
            "id": "android.aarch64.0",
            "name": "android.aarch64",
            "platform": "android",
            "path": "android.aarch64",
            "machines": ["aarch64"],
            "features": [],
            "filename": "_pytransform.so",
            "sha256": "f60cbe1a981347cb9e80d6f092340ec83d535e60f67890724397decc41bc2b66",
            "remark": "Build by android-ndk-r20/toolchains/llvm/prebuilt/linux-x86_64/bin/aarch64-linux-android21-clang"
        },
        {
            "id": "android.armv7.0",
            "name": "android.armv7",
            "platform": "android",
            "path": "android.armv7.0",
            "machines": ["armv7l"],
            "features": [],
            "filename": "_pytransform.so",
            "sha256": "f6d1e42abefc9978ea37de6d0b60e8db1b5051993e6d897da661ed0ed6bc6da6",
            "remark": "Build by android-ndk-r20/toolchains/llvm/prebuilt/linux-x86_64/bin/armv7a-linux-android21-clang"
        },
        {
            "id": "linux.ppc64.0",
            "name": "linux.ppc64",
            "platform": "linux",
            "path": "ppc64le",
            "machines": ["ppc64le"],
            "features": [],
            "filename": "_pytransform.so",
            "sha256": "ad88a0c714f81d960937ff31efcebed27da652cfd3bb29485c6c79513726b0e5",
            "remark": "For POWER8"
        },
        {
            "id": "darwin.arm64.0",
            "name": "darwin.arm64",
            "platform": "darwin",
            "path": "ios.arm64",
            "machines": ["arm64"],
            "features": [],
            "filename": "_pytransform.dylib",
            "sha256": "797f272a306b7eaa59ac95bbb5c8334cae291650a8310759d5406b5c9dceeaaa",
            "remark": "Built by CLang with iPhoneOS9.3.sdk"
        },
        {
            "id": "freebsd.x86_64.0",
            "name": "freebsd.x86_64",
            "platform": "freebsd",
            "path": "freebsd",
            "machines": ["x86_64"],
            "features": [],
            "filename": "_pytransform.so",
            "sha256": "1fef86a22220b899f111b1aae9a06ad443bfb2715fcccb4baff7e79aa97cb589",
            "remark": "Not support harddisk serial number"
        },
        {
            "id": "alpine.x86_64.0",
            "name": "alpine.x86_64",
            "platform": "alpine",
            "path": "alpine",
            "machines": ["x86_64"],
            "features": [],
            "filename": "_pytransform.so",
            "sha256": "5c91ddd79da0c405dcb01bef7db602d20765c46af2f1e60d5a90b819506246a2",
            "remark": "Built with musl-1.1.21 for Docker"
        },
        {
            "id": "alpine.arm.0",
            "name": "alpine.arm",
            "platform": "alpine",
            "path": "alpine.arm",
            "machines": ["armv5t", "armv7l"],
            "features": [],
            "filename": "_pytransform.so",
            "sha256": "4bed20b0f319dea63ddc4714f9f690a4c9ff26fb521fcf4f38eb8eda34fa5227",
            "remark": "Built with musl-1.1.21, 32 bit Armv5T, hard-float, little-endian"
        },
        {
            "id": "poky.x86.0",
            "name": "poky.x86",
            "platform": "linux",
            "path": "poky-i586",
            "machines": ["x86", "i386", "i486", "i586", "i686"],
            "features": [],
            "filename": "_pytransform.so",
            "sha256": "951462bf101de7483840691f187e4d45ccba47fcdd8c2f543619011809348826",
            "remark": "Work for Inel Quark, Cross compile by i586-poky-linux"
        },
        {
            "id": "centos6.x86_64.7",
            "name": "centos.x86_64",
            "platform": "linux",
            "path": "centos6.x86_64",
            "machines": ["x86_64", "amd64", "x64"],
            "features": ["JIT", "ANTI-DEBUG", "ADV"],
            "filename": "_pytransform.so",
            "sha256": "78fe2538f231f5c6b66b9a4fdf34839afc70562f080cd4f8d4bf71f9352aac72",
            "remark": "Cloned from linux.x86_64, patched for glibc < 2.14"
        },
        {
            "id": "windows.x86.0",
            "name": "windows.x86",
            "platform": "windows",
            "path": "windows.x86.0",
            "machines": ["x86"],
            "features": [],
            "filename": "_pytransform.dll",
            "sha256": "384e65e4d1321b353c0b90cf46aa5f2897d7323fbc1ccb31e54b42c022bf49e0",
            "remark": "Simple and quick, no any feature"
        },
        {
            "id": "windows.x86_64.0",
            "name": "windows.x86_64",
            "platform": "windows",
            "path": "windows.x86_64.0",
            "machines": ["amd64", "x86_64", "x64"],
            "features": [],
            "filename": "_pytransform.dll",
            "sha256": "9fba95ed1de3ff81ce31a88c00b92de0f1d74d0b7a72abe653e4071e5f777792",
            "remark": "Simple and quick, no any feature"
        },
        {
            "id": "linux.x86.0",
            "name": "linux.x86",
            "platform": "linux",
            "path": "linux.x86.0",
            "machines": ["i386", "i486", "i586", "i686", "x86"],
            "features": [],
            "filename": "_pytransform.so",
            "sha256": "9b818586ac6dd238bc9f0ed81ab4963b767032ff767dd6d19c351f6ffb88d90c",
            "remark": "Simple and quick, no any feature"
        },
        {
            "id": "linux.x86_64.0",
            "name": "linux.x86_64",
            "platform": "linux",
            "path": "linux.x86_64.0",
            "machines": ["x86_64", "amd64", "x64"],
            "features": [],
            "filename": "_pytransform.so",
            "sha256": "f91cb8be4c5b743767012a2d14b8b20cad28624501d8448d842e244ce2415bb5",
            "remark": "Simple and quick, no any feature"
        },
        {
            "id": "darwin.x86_64.0",
            "name": "darwin.x86_64",
            "platform": "darwin",
            "path": "darwin.x86_64.0",
            "machines": ["x86_64", "intel", "amd64", "x64"],
            "features": [],
            "filename": "_pytransform.dylib",
            "sha256": "070e6ebf3801c134f091cfd0f209cabba4750cce964c720d18f538df01247725",
            "remark": "Simple and quick, no any feature"
        },
        {
            "id": "linux.armv6.0",
            "name": "linux.armv6",
            "platform": "linux",
            "path": "linux.armv6.0",
            "machines": ["armv6l"],
            "features": [],
            "filename": "_pytransform.so",
            "sha256": "a694cbe5839c9bf96498a5423aa126c24aef8b7ec22ba98c0612f9f832fb72c0",
            "remark": "No any extra features, built with `-march=armv6 -mfloat-abi=hard -marm`"
        },
        {
            "id": "linux.armv7.0",
            "name": "linux.armv7",
            "platform": "linux",
            "path": "linux.armv7.0",
            "machines": ["armv7l"],
            "features": [],
            "filename": "_pytransform.so",
            "sha256": "439929783ed603f8b3bdaed63de0b4707af05435a0af8daade2ec5799f629b1b",
            "remark": "Simple and quick, no any feature"
        },
        {
            "id": "uclibc.armv7.0",
            "name": "uclibc.armv7",
            "platform": "linux",
            "path": "uclibc.armv7.0",
            "machines": ["armv7l"],
            "features": [],
            "filename": "_pytransform.so",
            "sha256": "99a3e314ff8bb1f95c07e47dd58990f4aae09dcfb7e997f8372aaf8ad7ba12c0",
            "remark": "No any feature, built by armv7-buildroot-uclibceabihf-gcc"
        },
        {
            "id": "linux.aarch32.0",
            "name": "linux.aarch32",
            "platform": "linux",
            "path": "linux.aarch32.0",
            "machines": ["aarch32"],
            "features": [],
            "filename": "_pytransform.so",
            "sha256": "75a1de442d5781a730349f4c4ff72f606c0f9a22169ee5281258c470b6bf29e2",
            "remark": "Simple and quick, no any feature"
        },
        {
            "id": "linux.aarch64.0",
            "name": "linux.aarch64",
            "platform": "linux",
            "path": "linux.aarch64.0",
            "machines": ["aarch64"],
            "features": [],
            "filename": "_pytransform.so",
            "sha256": "5f8076544b72631e7061c8d86c6685ee23b1d619dbebe85bb652da34532bac97",
            "remark": "Simple and quick, no any feature"
        }
    ]
}
